terver/__init__.py
terver/main.py
terver-1.0.4.dist-info/LICENSE.txt
terver-1.0.4.dist-info/METADATA
terver-1.0.4.dist-info/WHEEL
terver-1.0.4.dist-info/top_level.txt
terver-1.0.4.dist-info/RECORD
