Metadata-Version: 2.1
Name: terver
Version: 1.0.4
Summary: xD
Author: qdzzzxc
Author-email: nikitstp@gmail.com
Keywords: example python
Classifier: Programming Language :: Python :: 3.7
Classifier: License :: OSI Approved :: MIT License
Classifier: Operating System :: OS Independent
Requires-Python: >=3.7
License-File: LICENSE.txt
Requires-Dist: pyperclip (>=1.8.2)
